{
  "phase_1_critical_fixes": [
    {
      "action": "fix_format_mismatch",
      "parser": "Aws Vpc Dns",
      "current_format": "Key-Value",
      "target_format": "JSON",
      "generator_path": "/Users/nathanial.smalley/projects/jarvis_coding/Backend/event_generators/cloud_infrastructure/aws_vpc_dns.py",
      "priority": "CRITICAL"
    },
    {
      "action": "fix_format_mismatch",
      "parser": "Aws Vpcflowlogs",
      "current_format": "Key-Value",
      "target_format": "JSON",
      "generator_path": "/Users/nathanial.smalley/projects/jarvis_coding/Backend/event_generators/cloud_infrastructure/aws_vpcflowlogs.py",
      "priority": "CRITICAL"
    },
    {
      "action": "fix_format_mismatch",
      "parser": "Cisco Asa",
      "current_format": "Syslog",
      "target_format": "JSON",
      "generator_path": "/Users/nathanial.smalley/projects/jarvis_coding/Backend/event_generators/network_security/cisco_asa.py",
      "priority": "CRITICAL"
    },
    {
      "action": "fix_format_mismatch",
      "parser": "Cisco Isa3000",
      "current_format": "Key-Value",
      "target_format": "JSON",
      "generator_path": "/Users/nathanial.smalley/projects/jarvis_coding/Backend/event_generators/network_security/cisco_isa3000.py",
      "priority": "CRITICAL"
    },
    {
      "action": "fix_format_mismatch",
      "parser": "Cisco Meraki Flow",
      "current_format": "JSON",
      "target_format": "Syslog",
      "generator_path": "/Users/nathanial.smalley/projects/jarvis_coding/Backend/event_generators/network_security/cisco_meraki_flow.py",
      "priority": "CRITICAL"
    },
    {
      "action": "fix_format_mismatch",
      "parser": "Cisco Networks",
      "current_format": "Syslog",
      "target_format": "JSON",
      "generator_path": "/Users/nathanial.smalley/projects/jarvis_coding/Backend/event_generators/network_security/cisco_networks.py",
      "priority": "CRITICAL"
    },
    {
      "action": "fix_format_mismatch",
      "parser": "Cloudflare General",
      "current_format": "Key-Value",
      "target_format": "JSON",
      "generator_path": "/Users/nathanial.smalley/projects/jarvis_coding/Backend/event_generators/web_security/cloudflare_general.py",
      "priority": "CRITICAL"
    },
    {
      "action": "fix_format_mismatch",
      "parser": "Crowdstrike Falcon",
      "current_format": "Syslog",
      "target_format": "JSON",
      "generator_path": "/Users/nathanial.smalley/projects/jarvis_coding/Backend/event_generators/endpoint_security/crowdstrike_falcon.py",
      "priority": "CRITICAL"
    },
    {
      "action": "fix_format_mismatch",
      "parser": "Google Workspace",
      "current_format": "Syslog",
      "target_format": "JSON",
      "generator_path": "/Users/nathanial.smalley/projects/jarvis_coding/Backend/event_generators/cloud_infrastructure/google_workspace.py",
      "priority": "CRITICAL"
    }
  ],
  "phase_2_medium_fixes": [],
  "phase_3_improvements": [
    {
      "action": "add_star_trek_integration",
      "generator": "aws_cloudtrail",
      "priority": "HIGH"
    },
    {
      "action": "add_star_trek_integration",
      "generator": "aws_route53",
      "priority": "HIGH"
    },
    {
      "action": "add_star_trek_integration",
      "generator": "aws_vpc_dns",
      "priority": "HIGH"
    },
    {
      "action": "add_star_trek_integration",
      "generator": "aws_vpcflowlogs",
      "priority": "HIGH"
    },
    {
      "action": "add_star_trek_integration",
      "generator": "aws_waf",
      "priority": "HIGH"
    },
    {
      "action": "add_star_trek_integration",
      "generator": "cisco_asa",
      "priority": "HIGH"
    },
    {
      "action": "add_star_trek_integration",
      "generator": "cisco_ios",
      "priority": "HIGH"
    },
    {
      "action": "add_star_trek_integration",
      "generator": "cisco_isa3000",
      "priority": "HIGH"
    },
    {
      "action": "add_star_trek_integration",
      "generator": "cisco_ise",
      "priority": "HIGH"
    },
    {
      "action": "add_star_trek_integration",
      "generator": "cisco_meraki",
      "priority": "HIGH"
    },
    {
      "action": "add_star_trek_integration",
      "generator": "cisco_meraki_flow",
      "priority": "HIGH"
    },
    {
      "action": "add_star_trek_integration",
      "generator": "cisco_networks",
      "priority": "HIGH"
    },
    {
      "action": "add_star_trek_integration",
      "generator": "cyberark_conjur",
      "priority": "MEDIUM"
    },
    {
      "action": "add_star_trek_integration",
      "generator": "hashicorp_vault",
      "priority": "MEDIUM"
    },
    {
      "action": "add_star_trek_integration",
      "generator": "microsoft_azure_ad_signin",
      "priority": "HIGH"
    },
    {
      "action": "add_star_trek_integration",
      "generator": "microsoft_defender_email",
      "priority": "HIGH"
    },
    {
      "action": "add_star_trek_integration",
      "generator": "okta_authentication",
      "priority": "HIGH"
    },
    {
      "action": "add_star_trek_integration",
      "generator": "sentinelone_identity",
      "priority": "HIGH"
    },
    {
      "action": "add_star_trek_integration",
      "generator": "zscaler_firewall",
      "priority": "MEDIUM"
    },
    {
      "action": "add_star_trek_integration",
      "generator": "zscaler_private_access",
      "priority": "MEDIUM"
    }
  ],
  "phase_4_automation": [
    {
      "action": "create_format_validator",
      "description": "Validate generator output matches parser expectations"
    },
    {
      "action": "create_automated_tests",
      "description": "End-to-end parser-generator compatibility tests"
    },
    {
      "action": "add_ci_validation",
      "description": "Prevent format mismatches in CI/CD"
    },
    {
      "action": "create_generator_templates",
      "description": "Templates for creating new generators"
    }
  ]
}